text2tok.py
text2tok-1.2.0.dist-info/licenses/LICENSE
text2tok-1.2.0.dist-info/METADATA
text2tok-1.2.0.dist-info/WHEEL
text2tok-1.2.0.dist-info/top_level.txt
text2tok-1.2.0.dist-info/RECORD
