Metadata-Version: 2.4
Name: text2tok
Version: 1.2.0
Summary: Text tokenizers optimized for sparse retrieval.
Author-email: Li Peng-Hsuan <jacobvsdanniel@gmail.com>
License:                     GNU GENERAL PUBLIC LICENSE
Project-URL: Homepage, https://github.com/jacobvsdanniel/text2tok
Classifier: License :: OSI Approved :: GNU General Public License v3 (GPLv3)
Classifier: Programming Language :: Python :: 3
Classifier: Operating System :: OS Independent
Requires-Python: >=3.11
License-File: LICENSE
Requires-Dist: regex>=2025.9.1
Requires-Dist: transformers>=4.50.0
Dynamic: license-file
